texase/__init__.py
texase/addcolumn.py
texase/app.py
texase/data.py
texase/details.py
texase/edit.py
texase/files_io.py
texase/filter.py
texase/formatting.py
texase/help.py
texase/input_screens.py
texase/keys.py
texase/saved_columns.py
texase/search.py
texase/table.py
texase/texase.tcss
texase/validators.py
texase/yesno.py
texase-0.3.1.dist-info/METADATA
texase-0.3.1.dist-info/WHEEL
texase-0.3.1.dist-info/entry_points.txt
texase-0.3.1.dist-info/licenses/LICENSE
texase-0.3.1.dist-info/RECORD
