Metadata-Version: 2.4
Name: texase
Version: 0.3.1
Summary: Textual user interface for ASE db.
Author-email: Steen Lysgaard <stly@dtu.dk>
License-Expression: MPL-2.0
License-File: LICENSE
Requires-Python: ~=3.9
Requires-Dist: ase>=3.19.0
Requires-Dist: pandas<3,>=2.2.3
Requires-Dist: pillow>=11
Requires-Dist: pytest-xvfb<4,>=3.0.0
Requires-Dist: textual>=0.87.0
Requires-Dist: typer<0.10,>=0.9.0
Requires-Dist: typing-extensions>=4.12.2; python_full_version >= '3.13'
